odoo/addons/account_peppol_send_queue_job/README.rst
odoo/addons/account_peppol_send_queue_job/__init__.py
odoo/addons/account_peppol_send_queue_job/__manifest__.py
odoo/addons/account_peppol_send_queue_job/readme/CONTRIBUTORS.md
odoo/addons/account_peppol_send_queue_job/readme/CREDITS.md
odoo/addons/account_peppol_send_queue_job/readme/DESCRIPTION.md
odoo/addons/account_peppol_send_queue_job/static/description/icon.png
odoo/addons/account_peppol_send_queue_job/static/description/index.html
odoo/addons/account_peppol_send_queue_job/wizard/__init__.py
odoo/addons/account_peppol_send_queue_job/wizard/account_invoice_send.py
odoo_addon_account_peppol_send_queue_job-16.0.1.0.0.2.dist-info/METADATA
odoo_addon_account_peppol_send_queue_job-16.0.1.0.0.2.dist-info/WHEEL
odoo_addon_account_peppol_send_queue_job-16.0.1.0.0.2.dist-info/top_level.txt
odoo_addon_account_peppol_send_queue_job-16.0.1.0.0.2.dist-info/RECORD
