Metadata-Version: 2.1
Name: odoo-addon-account_peppol_send_queue_job
Version: 16.0.1.0.0.2
Requires-Python: >=3.10
Requires-Dist: odoo-addon-account_peppol_backport>=16.0dev,<16.1dev
Requires-Dist: odoo-addon-queue_job>=16.0dev,<16.1dev
Requires-Dist: odoo>=16.0a,<16.1dev
Summary: Send invoices to the Peppol accesspoint as queue jobs..
Home-page: https://github.com/acsone/odoo-peppol-backport
License: LGPL-3
Author: ACSONE SA/NV,Odoo Community Association (OCA)
Author-email: support@odoo-community.org
Classifier: Programming Language :: Python
Classifier: Framework :: Odoo
Classifier: Framework :: Odoo :: 16.0
Classifier: License :: OSI Approved :: GNU Lesser General Public License v3 (LGPLv3)
